{
  "canisters": {
    "estoy_out_icp_backend": {
      "main": "src/estoy_out_icp_backend/main.mo",
      "type": "motoko"
    },
    "estoy_out_icp_frontend": {
      "dependencies": [
        "estoy_out_icp_backend"
      ],
      "frontend": {
        "entrypoint": "src/estoy_out_icp_frontend/src/index.html"
      },
      "source": [
        "src/estoy_out_icp_frontend/assets",
        "dist/estoy_out_icp_frontend/"
      ],
      "type": "assets"
    }
  },
  "defaults": {
    "build": {
      "args": "",
      "packtool": ""
    }
  },
  "output_env_file": ".env",
  "version": 1
}